_bentoml_impl/frameworks/unsloth/__init__.py
_bentoml_impl/frameworks/unsloth/_version.py
_bentoml_impl/frameworks/unsloth/mapping.py
_bentoml_impl/frameworks/unsloth/template/.bentoignore
_bentoml_impl/frameworks/unsloth/template/.gitignore
_bentoml_impl/frameworks/unsloth/template/service.py
bentoml_unsloth-0.1.2.dist-info/METADATA
bentoml_unsloth-0.1.2.dist-info/WHEEL
bentoml_unsloth-0.1.2.dist-info/RECORD
